{"1048":{"id":"1048","name":"UMUNZE II","abbreviation":"16","local_government_id":"89","stateId":4,"lgaId":"20","pollingUnits":[{"id":"17942","name":"MBARIZO HALL","registration_area_id":"1048","precise_location":null,"abbreviation":"001","state":"04","lga":"20","ward":"16","units":"001","delimitation":"04/20/16/001","remark":"EXISTING PU"},{"id":"17943","name":"AGM SCHOOL","registration_area_id":"1048","precise_location":null,"abbreviation":"002","state":"04","lga":"20","ward":"16","units":"002","delimitation":"04/20/16/002","remark":"EXISTING PU"},{"id":"17944","name":"FCE (T) I","registration_area_id":"1048","precise_location":null,"abbreviation":"003","state":"04","lga":"20","ward":"16","units":"003","delimitation":"04/20/16/003","remark":"EXISTING PU"},{"id":"17945","name":"FCE (T) II","registration_area_id":"1048","precise_location":null,"abbreviation":"004","state":"04","lga":"20","ward":"16","units":"004","delimitation":"04/20/16/004","remark":"EXISTING PU"},{"id":"17946","name":"FCE (T) III","registration_area_id":"1048","precise_location":null,"abbreviation":"005","state":"04","lga":"20","ward":"16","units":"005","delimitation":"04/20/16/005","remark":"EXISTING PU"},{"id":"17947","name":"AMAUMEGBOKA SQUARE I","registration_area_id":"1048","precise_location":null,"abbreviation":"006","state":"04","lga":"20","ward":"16","units":"006","delimitation":"04/20/16/006","remark":"EXISTING PU"},{"id":"17948","name":"AMAUMEGBOKA SQUARE II","registration_area_id":"1048","precise_location":null,"abbreviation":"007","state":"04","lga":"20","ward":"16","units":"007","delimitation":"04/20/16/007","remark":"EXISTING PU"},{"id":"17949","name":"AMAUMEGBOKA SQUARE III","registration_area_id":"1048","precise_location":null,"abbreviation":"008","state":"04","lga":"20","ward":"16","units":"008","delimitation":"04/20/16/008","remark":"EXISTING PU"},{"id":"17950","name":"AMAUMEGBOKA SQUARE IV","registration_area_id":"1048","precise_location":null,"abbreviation":"009","state":"04","lga":"20","ward":"16","units":"009","delimitation":"04/20/16/009","remark":"EXISTING PU"},{"id":"17951","name":"AMAUMEGBOKA SQUARE V","registration_area_id":"1048","precise_location":null,"abbreviation":"010","state":"04","lga":"20","ward":"16","units":"010","delimitation":"04/20/16/010","remark":"EXISTING PU"},{"id":"17952","name":"NSOGWU SCHOOL","registration_area_id":"1048","precise_location":null,"abbreviation":"011","state":"04","lga":"20","ward":"16","units":"011","delimitation":"04/20/16/011","remark":"EXISTING PU"},{"id":"17953","name":"URUAGU PRY. SCHOOL I","registration_area_id":"1048","precise_location":null,"abbreviation":"012","state":"04","lga":"20","ward":"16","units":"012","delimitation":"04/20/16/012","remark":"EXISTING PU"},{"id":"17954","name":"URUAGU PRY. SCHOOL II","registration_area_id":"1048","precise_location":null,"abbreviation":"013","state":"04","lga":"20","ward":"16","units":"013","delimitation":"04/20/16/013","remark":"EXISTING PU"},{"id":"17955","name":"URUAGU PRY. SCHOOL III","registration_area_id":"1048","precise_location":null,"abbreviation":"014","state":"04","lga":"20","ward":"16","units":"014","delimitation":"04/20/16/014","remark":"EXISTING PU"},{"id":"17956","name":"MBARANGWU VILLAGE SQUARE I","registration_area_id":"1048","precise_location":null,"abbreviation":"015","state":"04","lga":"20","ward":"16","units":"015","delimitation":"04/20/16/015","remark":"EXISTING PU"},{"id":"17957","name":"MBARANGWU VILLAGE SQUARE II","registration_area_id":"1048","precise_location":null,"abbreviation":"016","state":"04","lga":"20","ward":"16","units":"016","delimitation":"04/20/16/016","remark":"EXISTING PU"},{"id":"17958","name":"MBARANGWU VILLAGE SQUARE III","registration_area_id":"1048","precise_location":null,"abbreviation":"017","state":"04","lga":"20","ward":"16","units":"017","delimitation":"04/20/16/017","remark":"EXISTING PU"},{"id":"17959","name":"MBARA OKENABO VILLAGE SQUARE I","registration_area_id":"1048","precise_location":null,"abbreviation":"018","state":"04","lga":"20","ward":"16","units":"018","delimitation":"04/20/16/018","remark":"EXISTING PU"},{"id":"17960","name":"MBARA OKENABO VILLAGE SQUARE II","registration_area_id":"1048","precise_location":null,"abbreviation":"019","state":"04","lga":"20","ward":"16","units":"019","delimitation":"04/20/16/019","remark":"EXISTING PU"},{"id":"17961","name":"OZARA PRY. SCHOOL","registration_area_id":"1048","precise_location":null,"abbreviation":"020","state":"04","lga":"20","ward":"16","units":"020","delimitation":"04/20/16/020","remark":"EXISTING PU"},{"id":"17962","name":"MBARA OJIAKO VILLAGE SQUARE","registration_area_id":"1048","precise_location":null,"abbreviation":"021","state":"04","lga":"20","ward":"16","units":"021","delimitation":"04/20/16/021","remark":"EXISTING PU"},{"id":"17963","name":"EUROPEAN QUARTERS","registration_area_id":"1048","precise_location":null,"abbreviation":"022","state":"04","lga":"20","ward":"16","units":"022","delimitation":"04/20/16/022","remark":"NEW PU"}]}}