{"1674":{"id":"1674","name":"LASSA","abbreviation":"06","local_government_id":"143","stateId":8,"lgaId":"02","pollingUnits":[{"id":"31109","name":"MOTOR PARK I","registration_area_id":"1674","precise_location":null,"abbreviation":"001","state":"08","lga":"02","ward":"06","units":"001","delimitation":"08/02/06/001","remark":"EXISTING PU"},{"id":"31110","name":"MOTOR PARK II","registration_area_id":"1674","precise_location":null,"abbreviation":"002","state":"08","lga":"02","ward":"06","units":"002","delimitation":"08/02/06/002","remark":"EXISTING PU"},{"id":"31111","name":"MALA THLAWUR","registration_area_id":"1674","precise_location":null,"abbreviation":"003","state":"08","lga":"02","ward":"06","units":"003","delimitation":"08/02/06/003","remark":"EXISTING PU"},{"id":"31112","name":"KOFAR KATSALLA  I","registration_area_id":"1674","precise_location":null,"abbreviation":"004","state":"08","lga":"02","ward":"06","units":"004","delimitation":"08/02/06/004","remark":"EXISTING PU"},{"id":"31113","name":"KOFAR KATSALLA  II","registration_area_id":"1674","precise_location":null,"abbreviation":"005","state":"08","lga":"02","ward":"06","units":"005","delimitation":"08/02/06/005","remark":"EXISTING PU"},{"id":"31114","name":"MALLAM WAMPANA  I","registration_area_id":"1674","precise_location":null,"abbreviation":"006","state":"08","lga":"02","ward":"06","units":"006","delimitation":"08/02/06/006","remark":"EXISTING PU"},{"id":"31115","name":"MALLAM WAMPANA II","registration_area_id":"1674","precise_location":null,"abbreviation":"007","state":"08","lga":"02","ward":"06","units":"007","delimitation":"08/02/06/007","remark":"EXISTING PU"},{"id":"31116","name":"U.P.E. PRI. SCH.  I","registration_area_id":"1674","precise_location":null,"abbreviation":"008","state":"08","lga":"02","ward":"06","units":"008","delimitation":"08/02/06/008","remark":"EXISTING PU"},{"id":"31117","name":"U.P.E. PRI. SCH.  II","registration_area_id":"1674","precise_location":null,"abbreviation":"009","state":"08","lga":"02","ward":"06","units":"009","delimitation":"08/02/06/009","remark":"EXISTING PU"},{"id":"31118","name":"G.D.S.S LASSA","registration_area_id":"1674","precise_location":null,"abbreviation":"010","state":"08","lga":"02","ward":"06","units":"010","delimitation":"08/02/06/010","remark":"EXISTING PU"},{"id":"31119","name":"SAMUWA PRI. SCH.","registration_area_id":"1674","precise_location":null,"abbreviation":"011","state":"08","lga":"02","ward":"06","units":"011","delimitation":"08/02/06/011","remark":"EXISTING PU"},{"id":"31120","name":"KOFAR LAWAN","registration_area_id":"1674","precise_location":null,"abbreviation":"012","state":"08","lga":"02","ward":"06","units":"012","delimitation":"08/02/06/012","remark":"EXISTING PU"},{"id":"31121","name":"BAKIN KASUWA LASSA","registration_area_id":"1674","precise_location":null,"abbreviation":"013","state":"08","lga":"02","ward":"06","units":"013","delimitation":"08/02/06/013","remark":"NEW PU"}]}}