{"17636":{"id":"17636","name":"ARAROMI OBU","abbreviation":"04","local_government_id":"594","stateId":28,"lgaId":"13","pollingUnits":[{"id":"347157","name":"L.A PRY SCH AREA ARAROMI OBU, L.A PRY SCH AREA ARAROMI OBU NORTH","registration_area_id":"17636","precise_location":null,"abbreviation":"001","state":"28","lga":"13","ward":"04","units":"001","delimitation":"28/13/04/001","remark":"EXISTING PU"},{"id":"347158","name":"L.A PRY SCH AREA ARAROMI OBU, L.A PRY SCH AREA ARAROMI OBU SOUTH","registration_area_id":"17636","precise_location":null,"abbreviation":"002","state":"28","lga":"13","ward":"04","units":"002","delimitation":"28/13/04/002","remark":"EXISTING PU"},{"id":"347159","name":"COURT HALL AREA ARAROMI OBU, COURT HALL AREA ARAROMI OBU NORTH","registration_area_id":"17636","precise_location":null,"abbreviation":"003","state":"28","lga":"13","ward":"04","units":"003","delimitation":"28/13/04/003","remark":"EXISTING PU"},{"id":"347160","name":"COURT HALL AREA ARAROMI OBU, COURT HALL AREA ARAROMI OBU SOUTH","registration_area_id":"17636","precise_location":null,"abbreviation":"004","state":"28","lga":"13","ward":"04","units":"004","delimitation":"28/13/04/004","remark":"EXISTING PU"},{"id":"347161","name":"COMM HEALTH CENTRE ARAROMI OBU, COMM HEALTH CENTRE ARAROMI OBU NORTH","registration_area_id":"17636","precise_location":null,"abbreviation":"005","state":"28","lga":"13","ward":"04","units":"005","delimitation":"28/13/04/005","remark":"EXISTING PU"},{"id":"347162","name":"COMM HEALTH CENTRE ARAROMI OBU, COMM HEALTH CENTRE ARAROMI OBU SOUTH","registration_area_id":"17636","precise_location":null,"abbreviation":"006","state":"28","lga":"13","ward":"04","units":"006","delimitation":"28/13/04/006","remark":"EXISTING PU"},{"id":"347163","name":"COMM HIGH SCH ARAROIMI OBU, COMM HIGH SCH ARAROIMI OBU","registration_area_id":"17636","precise_location":null,"abbreviation":"007","state":"28","lga":"13","ward":"04","units":"007","delimitation":"28/13/04/007","remark":"EXISTING PU"},{"id":"347164","name":"MATERNITY CENTRE 1 ARAROMI, MATERNITY CENTRE  ARAROMI","registration_area_id":"17636","precise_location":null,"abbreviation":"008","state":"28","lga":"13","ward":"04","units":"008","delimitation":"28/13/04/008","remark":"EXISTING PU"},{"id":"347165","name":"MATERNITY CENTRE 11 ARAROMI, MATERNITY CENTRE  ARAROMI","registration_area_id":"17636","precise_location":null,"abbreviation":"009","state":"28","lga":"13","ward":"04","units":"009","delimitation":"28/13/04/009","remark":"EXISTING PU"},{"id":"347166","name":"COMM PRY SCH ARAROMI OBU, COMM PRY SCH ARAROMI OBU  NORTH","registration_area_id":"17636","precise_location":null,"abbreviation":"010","state":"28","lga":"13","ward":"04","units":"010","delimitation":"28/13/04/010","remark":"EXISTING PU"},{"id":"347167","name":"COMM PRY SCH ARAROMI OBU, COMM PRY SCH ARAROMI OBU  SOUTH","registration_area_id":"17636","precise_location":null,"abbreviation":"011","state":"28","lga":"13","ward":"04","units":"011","delimitation":"28/13/04/011","remark":"EXISTING PU"},{"id":"347168","name":"ADAJA TEMIDIRE CAMP, CANTRE OF  ADAJA TEMIDIRE CAMP","registration_area_id":"17636","precise_location":null,"abbreviation":"012","state":"28","lga":"13","ward":"04","units":"012","delimitation":"28/13/04/012","remark":"EXISTING PU"},{"id":"347169","name":"ENUJOWO/AGBALA JAMES CAMP, CENTRE OF ENUJOWO ARAROMI OBU","registration_area_id":"17636","precise_location":null,"abbreviation":"013","state":"28","lga":"13","ward":"04","units":"013","delimitation":"28/13/04/013","remark":"EXISTING PU"},{"id":"347170","name":"AGBOLIGI JAGIDI VILLAGE, CENTRE OF AGBOLIGI JAGIDI VILLAGE  NORTH","registration_area_id":"17636","precise_location":null,"abbreviation":"014","state":"28","lga":"13","ward":"04","units":"014","delimitation":"28/13/04/014","remark":"EXISTING PU"},{"id":"347171","name":"AGBOLIGI JAGIDI VILLAGE, CENTRE OF AGBOLIGI JAGIDI VILLAGE  SOUTH","registration_area_id":"17636","precise_location":null,"abbreviation":"015","state":"28","lga":"13","ward":"04","units":"015","delimitation":"28/13/04/015","remark":"EXISTING PU"},{"id":"347172","name":"OLOMI OTORO CAMP LIKEBE VILLAGE, CENTRE OF LIKEBE VILLAGE NORTH","registration_area_id":"17636","precise_location":null,"abbreviation":"016","state":"28","lga":"13","ward":"04","units":"016","delimitation":"28/13/04/016","remark":"EXISTING PU"},{"id":"347173","name":"OLOMI OTORO CAMP LIKEBE VILLAGE, LOGHE/AYETUNMARA VILLAGE CENTRE","registration_area_id":"17636","precise_location":null,"abbreviation":"017","state":"28","lga":"13","ward":"04","units":"017","delimitation":"28/13/04/017","remark":"EXISTING PU"}]}}