{"17929":{"id":"17929","name":"IDOGUN WARD","abbreviation":"05","local_government_id":"619","stateId":29,"lgaId":"22","pollingUnits":[{"id":"351107","name":"AWORIN SADIKU ADC PRY SCH","registration_area_id":"17929","precise_location":null,"abbreviation":"001","state":"29","lga":"22","ward":"05","units":"001","delimitation":"29/22/05/001","remark":"EXISTING PU"},{"id":"351108","name":"A.U.D PRY. SCHOOL, OLOKUTA","registration_area_id":"17929","precise_location":null,"abbreviation":"002","state":"29","lga":"22","ward":"05","units":"002","delimitation":"29/22/05/002","remark":"EXISTING PU"},{"id":"351109","name":"HOLY TRINITY, LASEGBA","registration_area_id":"17929","precise_location":null,"abbreviation":"003","state":"29","lga":"22","ward":"05","units":"003","delimitation":"29/22/05/003","remark":"EXISTING PU"},{"id":"351110","name":"IWARI ADEFI, PRY. SCHOL","registration_area_id":"17929","precise_location":null,"abbreviation":"004","state":"29","lga":"22","ward":"05","units":"004","delimitation":"29/22/05/004","remark":"EXISTING PU"},{"id":"351111","name":"ERUKU VILLAGE","registration_area_id":"17929","precise_location":null,"abbreviation":"005","state":"29","lga":"22","ward":"05","units":"005","delimitation":"29/22/05/005","remark":"EXISTING PU"},{"id":"351112","name":"COMMUNITY PRY. SCH. AWORIN BADIRU IKOYI","registration_area_id":"17929","precise_location":null,"abbreviation":"006","state":"29","lga":"22","ward":"05","units":"006","delimitation":"29/22/05/006","remark":"NEW PU"}]}}