{"18262":{"id":"18262","name":"AKATA","abbreviation":"01","local_government_id":"649","stateId":30,"lgaId":"22","pollingUnits":[{"id":"356931","name":"ODE ALAKASU I","registration_area_id":"18262","precise_location":null,"abbreviation":"001","state":"30","lga":"22","ward":"01","units":"001","delimitation":"30/22/01/001","remark":"EXISTING PU"},{"id":"356932","name":"ODE ALAKASU II","registration_area_id":"18262","precise_location":null,"abbreviation":"002","state":"30","lga":"22","ward":"01","units":"002","delimitation":"30/22/01/002","remark":"EXISTING PU"},{"id":"356933","name":"ODE ONIYO I","registration_area_id":"18262","precise_location":null,"abbreviation":"003","state":"30","lga":"22","ward":"01","units":"003","delimitation":"30/22/01/003","remark":"EXISTING PU"},{"id":"356934","name":"ODE ONIYO II","registration_area_id":"18262","precise_location":null,"abbreviation":"004","state":"30","lga":"22","ward":"01","units":"004","delimitation":"30/22/01/004","remark":"EXISTING PU"},{"id":"356935","name":"ODE DAODU I","registration_area_id":"18262","precise_location":null,"abbreviation":"005","state":"30","lga":"22","ward":"01","units":"005","delimitation":"30/22/01/005","remark":"EXISTING PU"},{"id":"356936","name":"ODE DAODU II","registration_area_id":"18262","precise_location":null,"abbreviation":"006","state":"30","lga":"22","ward":"01","units":"006","delimitation":"30/22/01/006","remark":"EXISTING PU"},{"id":"356937","name":"AYEGUN PRIMARY SCHOOL I","registration_area_id":"18262","precise_location":null,"abbreviation":"007","state":"30","lga":"22","ward":"01","units":"007","delimitation":"30/22/01/007","remark":"EXISTING PU"},{"id":"356938","name":"AYEGUN PRIMARY SCHOOL II","registration_area_id":"18262","precise_location":null,"abbreviation":"008","state":"30","lga":"22","ward":"01","units":"008","delimitation":"30/22/01/008","remark":"EXISTING PU"},{"id":"356939","name":"ODE ONIDEURE I","registration_area_id":"18262","precise_location":null,"abbreviation":"009","state":"30","lga":"22","ward":"01","units":"009","delimitation":"30/22/01/009","remark":"EXISTING PU"},{"id":"356940","name":"ODE ONIDEURE II","registration_area_id":"18262","precise_location":null,"abbreviation":"010","state":"30","lga":"22","ward":"01","units":"010","delimitation":"30/22/01/010","remark":"EXISTING PU"},{"id":"356941","name":"ODE ONIDEURE III","registration_area_id":"18262","precise_location":null,"abbreviation":"011","state":"30","lga":"22","ward":"01","units":"011","delimitation":"30/22/01/011","remark":"EXISTING PU"},{"id":"356942","name":"ODE ADEOYE I","registration_area_id":"18262","precise_location":null,"abbreviation":"012","state":"30","lga":"22","ward":"01","units":"012","delimitation":"30/22/01/012","remark":"EXISTING PU"},{"id":"356943","name":"ODE ADEOYE II","registration_area_id":"18262","precise_location":null,"abbreviation":"013","state":"30","lga":"22","ward":"01","units":"013","delimitation":"30/22/01/013","remark":"EXISTING PU"},{"id":"356944","name":"ODE MOINMOIN I","registration_area_id":"18262","precise_location":null,"abbreviation":"014","state":"30","lga":"22","ward":"01","units":"014","delimitation":"30/22/01/014","remark":"EXISTING PU"},{"id":"356945","name":"ODE MOINMOIN II","registration_area_id":"18262","precise_location":null,"abbreviation":"015","state":"30","lga":"22","ward":"01","units":"015","delimitation":"30/22/01/015","remark":"EXISTING PU"},{"id":"356946","name":"ODE AJIBADE I","registration_area_id":"18262","precise_location":null,"abbreviation":"016","state":"30","lga":"22","ward":"01","units":"016","delimitation":"30/22/01/016","remark":"EXISTING PU"},{"id":"356947","name":"ODE AJIBADE II","registration_area_id":"18262","precise_location":null,"abbreviation":"017","state":"30","lga":"22","ward":"01","units":"017","delimitation":"30/22/01/017","remark":"EXISTING PU"},{"id":"356948","name":"ODE ALARO","registration_area_id":"18262","precise_location":null,"abbreviation":"018","state":"30","lga":"22","ward":"01","units":"018","delimitation":"30/22/01/018","remark":"EXISTING PU"},{"id":"356949","name":"AYEGUN PRY SCHOOL III","registration_area_id":"18262","precise_location":null,"abbreviation":"019","state":"30","lga":"22","ward":"01","units":"019","delimitation":"30/22/01/019","remark":"NEW PU"}]}}