{"18403":{"id":"18403","name":"KASURU","abbreviation":"08","local_government_id":"769","stateId":31,"lgaId":"02","pollingUnits":[{"id":"359103","name":"FICHIZA I","registration_area_id":"18403","precise_location":null,"abbreviation":"001","state":"31","lga":"02","ward":"08","units":"001","delimitation":"31/02/08/001","remark":"EXISTING PU"},{"id":"359104","name":"FICHIZA II","registration_area_id":"18403","precise_location":null,"abbreviation":"002","state":"31","lga":"02","ward":"08","units":"002","delimitation":"31/02/08/002","remark":"EXISTING PU"},{"id":"359105","name":"FULOTI I","registration_area_id":"18403","precise_location":null,"abbreviation":"003","state":"31","lga":"02","ward":"08","units":"003","delimitation":"31/02/08/003","remark":"EXISTING PU"},{"id":"359106","name":"FULOTI II","registration_area_id":"18403","precise_location":null,"abbreviation":"004","state":"31","lga":"02","ward":"08","units":"004","delimitation":"31/02/08/004","remark":"EXISTING PU"},{"id":"359107","name":"AMO JANJI","registration_area_id":"18403","precise_location":null,"abbreviation":"005","state":"31","lga":"02","ward":"08","units":"005","delimitation":"31/02/08/005","remark":"EXISTING PU"},{"id":"359108","name":"NANLI","registration_area_id":"18403","precise_location":null,"abbreviation":"006","state":"31","lga":"02","ward":"08","units":"006","delimitation":"31/02/08/006","remark":"EXISTING PU"},{"id":"359109","name":"GAGARAU","registration_area_id":"18403","precise_location":null,"abbreviation":"007","state":"31","lga":"02","ward":"08","units":"007","delimitation":"31/02/08/007","remark":"NEW PU"},{"id":"359110","name":"ULANI","registration_area_id":"18403","precise_location":null,"abbreviation":"008","state":"31","lga":"02","ward":"08","units":"008","delimitation":"31/02/08/008","remark":"NEW PU"},{"id":"359111","name":"KUNIRI","registration_area_id":"18403","precise_location":null,"abbreviation":"009","state":"31","lga":"02","ward":"08","units":"009","delimitation":"31/02/08/009","remark":"NEW PU"},{"id":"359112","name":"GSS KAWAM","registration_area_id":"18403","precise_location":null,"abbreviation":"010","state":"31","lga":"02","ward":"08","units":"010","delimitation":"31/02/08/010","remark":"NEW PU"},{"id":"359113","name":"TIGADAM","registration_area_id":"18403","precise_location":null,"abbreviation":"011","state":"31","lga":"02","ward":"08","units":"011","delimitation":"31/02/08/011","remark":"NEW PU"},{"id":"359114","name":"UDOZOH","registration_area_id":"18403","precise_location":null,"abbreviation":"012","state":"31","lga":"02","ward":"08","units":"012","delimitation":"31/02/08/012","remark":"NEW PU"},{"id":"359115","name":"LUWARAM","registration_area_id":"18403","precise_location":null,"abbreviation":"013","state":"31","lga":"02","ward":"08","units":"013","delimitation":"31/02/08/013","remark":"NEW PU"}]}}