{"1907":{"id":"1907","name":"KULLI","abbreviation":"07","local_government_id":"163","stateId":8,"lgaId":"22","pollingUnits":[{"id":"35329","name":"KULLI PRI. SCH. I","registration_area_id":"1907","precise_location":null,"abbreviation":"001","state":"08","lga":"22","ward":"07","units":"001","delimitation":"08/22/07/001","remark":"EXISTING PU"},{"id":"35330","name":"KULLI PRI. SCH. II","registration_area_id":"1907","precise_location":null,"abbreviation":"002","state":"08","lga":"22","ward":"07","units":"002","delimitation":"08/22/07/002","remark":"EXISTING PU"},{"id":"35331","name":"DAULA","registration_area_id":"1907","precise_location":null,"abbreviation":"003","state":"08","lga":"22","ward":"07","units":"003","delimitation":"08/22/07/003","remark":"EXISTING PU"},{"id":"35332","name":"ZUWA","registration_area_id":"1907","precise_location":null,"abbreviation":"004","state":"08","lga":"22","ward":"07","units":"004","delimitation":"08/22/07/004","remark":"EXISTING PU"},{"id":"35333","name":"BULAMELERI  I","registration_area_id":"1907","precise_location":null,"abbreviation":"005","state":"08","lga":"22","ward":"07","units":"005","delimitation":"08/22/07/005","remark":"EXISTING PU"},{"id":"35334","name":"BULAMELERI  II","registration_area_id":"1907","precise_location":null,"abbreviation":"006","state":"08","lga":"22","ward":"07","units":"006","delimitation":"08/22/07/006","remark":"EXISTING PU"},{"id":"35335","name":"MOMO KURA","registration_area_id":"1907","precise_location":null,"abbreviation":"007","state":"08","lga":"22","ward":"07","units":"007","delimitation":"08/22/07/007","remark":"EXISTING PU"},{"id":"35336","name":"ALAM DORI","registration_area_id":"1907","precise_location":null,"abbreviation":"008","state":"08","lga":"22","ward":"07","units":"008","delimitation":"08/22/07/008","remark":"EXISTING PU"},{"id":"35337","name":"MAULA CHINGONA","registration_area_id":"1907","precise_location":null,"abbreviation":"009","state":"08","lga":"22","ward":"07","units":"009","delimitation":"08/22/07/009","remark":"EXISTING PU"},{"id":"35338","name":"MUNTUNA","registration_area_id":"1907","precise_location":null,"abbreviation":"010","state":"08","lga":"22","ward":"07","units":"010","delimitation":"08/22/07/010","remark":"EXISTING PU"},{"id":"35339","name":"MAMA KURA","registration_area_id":"1907","precise_location":null,"abbreviation":"011","state":"08","lga":"22","ward":"07","units":"011","delimitation":"08/22/07/011","remark":"EXISTING PU"},{"id":"35340","name":"LAMARE","registration_area_id":"1907","precise_location":null,"abbreviation":"012","state":"08","lga":"22","ward":"07","units":"012","delimitation":"08/22/07/012","remark":"NEW PU"}]}}