{"19361":{"id":"19361","name":"SHOYE/GARIN ABA","abbreviation":"08","local_government_id":"741","stateId":35,"lgaId":"04","pollingUnits":[{"id":"378844","name":"BALDE, BALDE PRI. SCH.","registration_area_id":"19361","precise_location":null,"abbreviation":"001","state":"35","lga":"04","ward":"08","units":"001","delimitation":"35/04/08/001","remark":"EXISTING PU"},{"id":"378845","name":"GARIN ABBA, PRI. SCH. I","registration_area_id":"19361","precise_location":null,"abbreviation":"002","state":"35","lga":"04","ward":"08","units":"002","delimitation":"35/04/08/002","remark":"EXISTING PU"},{"id":"378846","name":"GARIN ABBA, PRI. SCH. II","registration_area_id":"19361","precise_location":null,"abbreviation":"003","state":"35","lga":"04","ward":"08","units":"003","delimitation":"35/04/08/003","remark":"EXISTING PU"},{"id":"378847","name":"GARIN DAUYA, PRI. SCH.","registration_area_id":"19361","precise_location":null,"abbreviation":"004","state":"35","lga":"04","ward":"08","units":"004","delimitation":"35/04/08/004","remark":"EXISTING PU"},{"id":"378848","name":"GASHINGE PRI. SCH.","registration_area_id":"19361","precise_location":null,"abbreviation":"005","state":"35","lga":"04","ward":"08","units":"005","delimitation":"35/04/08/005","remark":"EXISTING PU"},{"id":"378849","name":"LAMPO, KOFAR MAI UNGUWA","registration_area_id":"19361","precise_location":null,"abbreviation":"006","state":"35","lga":"04","ward":"08","units":"006","delimitation":"35/04/08/006","remark":"EXISTING PU"},{"id":"378850","name":"GASHINGE PRI. SCH.","registration_area_id":"19361","precise_location":null,"abbreviation":"007","state":"35","lga":"04","ward":"08","units":"007","delimitation":"35/04/08/007","remark":"NEW PU"},{"id":"378851","name":"GARIN ABBA PRI. SCH","registration_area_id":"19361","precise_location":null,"abbreviation":"008","state":"35","lga":"04","ward":"08","units":"008","delimitation":"35/04/08/008","remark":"NEW PU"},{"id":"378852","name":"GARIN DAUYA, PRI. SCH.","registration_area_id":"19361","precise_location":null,"abbreviation":"009","state":"35","lga":"04","ward":"08","units":"009","delimitation":"35/04/08/009","remark":"NEW PU"}]}}