{"2055":{"id":"2055","name":"THREE (3)","abbreviation":"03","local_government_id":"177","stateId":9,"lgaId":"09","pollingUnits":[{"id":"37374","name":"DUKE TOWN PRIMARY SCHOOL","registration_area_id":"2055","precise_location":null,"abbreviation":"001","state":"09","lga":"09","ward":"03","units":"001","delimitation":"09/09/03/001","remark":"EXISTING PU"},{"id":"37375","name":"BEECROFT/NKWA STREET","registration_area_id":"2055","precise_location":null,"abbreviation":"002","state":"09","lga":"09","ward":"03","units":"002","delimitation":"09/09/03/002","remark":"EXISTING PU"},{"id":"37376","name":"OFFIONG SQUARE","registration_area_id":"2055","precise_location":null,"abbreviation":"003","state":"09","lga":"09","ward":"03","units":"003","delimitation":"09/09/03/003","remark":"EXISTING PU"},{"id":"37377","name":"EYAMBA/OFFIONG STREET","registration_area_id":"2055","precise_location":null,"abbreviation":"004","state":"09","lga":"09","ward":"03","units":"004","delimitation":"09/09/03/004","remark":"EXISTING PU"},{"id":"37378","name":"EYO EDEM/OFFIONG STREET","registration_area_id":"2055","precise_location":null,"abbreviation":"005","state":"09","lga":"09","ward":"03","units":"005","delimitation":"09/09/03/005","remark":"EXISTING PU"},{"id":"37379","name":"NATIVE COURT","registration_area_id":"2055","precise_location":null,"abbreviation":"006","state":"09","lga":"09","ward":"03","units":"006","delimitation":"09/09/03/006","remark":"EXISTING PU"},{"id":"37380","name":"EDEM STREET/ARCHIBONG STREET","registration_area_id":"2055","precise_location":null,"abbreviation":"007","state":"09","lga":"09","ward":"03","units":"007","delimitation":"09/09/03/007","remark":"EXISTING PU"},{"id":"37381","name":"HEWETT/WATT I","registration_area_id":"2055","precise_location":null,"abbreviation":"008","state":"09","lga":"09","ward":"03","units":"008","delimitation":"09/09/03/008","remark":"EXISTING PU"},{"id":"37382","name":"HEWETT/WATT II","registration_area_id":"2055","precise_location":null,"abbreviation":"009","state":"09","lga":"09","ward":"03","units":"009","delimitation":"09/09/03/009","remark":"EXISTING PU"},{"id":"37383","name":"OPEN SPAPCE BEHIND PRESBYTERIAN CHURCH DUKE TOWN","registration_area_id":"2055","precise_location":null,"abbreviation":"010","state":"09","lga":"09","ward":"03","units":"010","delimitation":"09/09/03/010","remark":"NEW PU"},{"id":"37384","name":"NATIVE COURT II","registration_area_id":"2055","precise_location":null,"abbreviation":"011","state":"09","lga":"09","ward":"03","units":"011","delimitation":"09/09/03/011","remark":"NEW PU"},{"id":"37385","name":"OPEN SPACE SHOPPING MALL OPP. WATT MARKET","registration_area_id":"2055","precise_location":null,"abbreviation":"012","state":"09","lga":"09","ward":"03","units":"012","delimitation":"09/09/03/012","remark":"NEW PU"},{"id":"37386","name":"OPEN SPACE HEWETT BY EYO EDEM JUNCTION","registration_area_id":"2055","precise_location":null,"abbreviation":"013","state":"09","lga":"09","ward":"03","units":"013","delimitation":"09/09/03/013","remark":"NEW PU"}]}}