{"2138":{"id":"2138","name":"OGOJA URBAN I","abbreviation":"09","local_government_id":"184","stateId":9,"lgaId":"16","pollingUnits":[{"id":"38782","name":"HOLY CHILD CONVENT PRIMARY SCHOOL, AGIGA I","registration_area_id":"2138","precise_location":null,"abbreviation":"001","state":"09","lga":"16","ward":"09","units":"001","delimitation":"09/16/09/001","remark":"EXISTING PU"},{"id":"38783","name":"HOLY CHILD CONVENT PRIMARY SCHOOL, AGIGA II","registration_area_id":"2138","precise_location":null,"abbreviation":"002","state":"09","lga":"16","ward":"09","units":"002","delimitation":"09/16/09/002","remark":"EXISTING PU"},{"id":"38784","name":"HOLY CHILD CONVENT PRIMARY SCHOOL, AGIGA III","registration_area_id":"2138","precise_location":null,"abbreviation":"003","state":"09","lga":"16","ward":"09","units":"003","delimitation":"09/16/09/003","remark":"EXISTING PU"},{"id":"38785","name":"GARKI OKUKU ROAD","registration_area_id":"2138","precise_location":null,"abbreviation":"004","state":"09","lga":"16","ward":"09","units":"004","delimitation":"09/16/09/004","remark":"EXISTING PU"},{"id":"38786","name":"ST. BEN'S DEM PRIMARY SCHOOL IGOLI. I","registration_area_id":"2138","precise_location":null,"abbreviation":"005","state":"09","lga":"16","ward":"09","units":"005","delimitation":"09/16/09/005","remark":"EXISTING PU"},{"id":"38787","name":"ST. BEN'S DEM. PRIMARY SCHOOL, IGOLI. II","registration_area_id":"2138","precise_location":null,"abbreviation":"006","state":"09","lga":"16","ward":"09","units":"006","delimitation":"09/16/09/006","remark":"EXISTING PU"},{"id":"38788","name":"MATERNITY HOSPITAL MONIAYA","registration_area_id":"2138","precise_location":null,"abbreviation":"007","state":"09","lga":"16","ward":"09","units":"007","delimitation":"09/16/09/007","remark":"EXISTING PU"},{"id":"38789","name":"NEAR B.I.R. OFFICE","registration_area_id":"2138","precise_location":null,"abbreviation":"008","state":"09","lga":"16","ward":"09","units":"008","delimitation":"09/16/09/008","remark":"EXISTING PU"},{"id":"38790","name":"PLAY GROUND UKAMUSHA, ISHIBORI. I","registration_area_id":"2138","precise_location":null,"abbreviation":"009","state":"09","lga":"16","ward":"09","units":"009","delimitation":"09/16/09/009","remark":"EXISTING PU"},{"id":"38791","name":"PLAY GROUND IKAPTANG, ISHIBORI. II","registration_area_id":"2138","precise_location":null,"abbreviation":"010","state":"09","lga":"16","ward":"09","units":"010","delimitation":"09/16/09/010","remark":"EXISTING PU"},{"id":"38792","name":"ST. ANDREW'S PRIMARY SCHOOL I","registration_area_id":"2138","precise_location":null,"abbreviation":"011","state":"09","lga":"16","ward":"09","units":"011","delimitation":"09/16/09/011","remark":"EXISTING PU"},{"id":"38793","name":"ST. ANDREW'S PRIMARY SCHOOL I","registration_area_id":"2138","precise_location":null,"abbreviation":"012","state":"09","lga":"16","ward":"09","units":"012","delimitation":"09/16/09/012","remark":"EXISTING PU"},{"id":"38794","name":"PLAY GROUND,   ISHIBORI","registration_area_id":"2138","precise_location":null,"abbreviation":"013","state":"09","lga":"16","ward":"09","units":"013","delimitation":"09/16/09/013","remark":"EXISTING PU"},{"id":"38795","name":"ST. BEN'S PRIMARY SCHOOL,  OGOLI I","registration_area_id":"2138","precise_location":null,"abbreviation":"014","state":"09","lga":"16","ward":"09","units":"014","delimitation":"09/16/09/014","remark":"EXISTING PU"},{"id":"38796","name":"ST. BEN'S PRIMARY SCHOOL,  OGOLI II","registration_area_id":"2138","precise_location":null,"abbreviation":"015","state":"09","lga":"16","ward":"09","units":"015","delimitation":"09/16/09/015","remark":"EXISTING PU"},{"id":"38797","name":"ST. BEN'S PRIMARY SCHOOL,  OGOLI III","registration_area_id":"2138","precise_location":null,"abbreviation":"016","state":"09","lga":"16","ward":"09","units":"016","delimitation":"09/16/09/016","remark":"EXISTING PU"},{"id":"38798","name":"ST. BEN'S PRIMARY SCHOOL,  OGOLI IV","registration_area_id":"2138","precise_location":null,"abbreviation":"017","state":"09","lga":"16","ward":"09","units":"017","delimitation":"09/16/09/017","remark":"EXISTING PU"},{"id":"38799","name":"PLAYGROUND ISHIBORI","registration_area_id":"2138","precise_location":null,"abbreviation":"018","state":"09","lga":"16","ward":"09","units":"018","delimitation":"09/16/09/018","remark":"EXISTING PU"},{"id":"38800","name":"TIMBER MARKET IBADAN STREET","registration_area_id":"2138","precise_location":null,"abbreviation":"019","state":"09","lga":"16","ward":"09","units":"019","delimitation":"09/16/09/019","remark":"NEW PU"},{"id":"38801","name":"AGIGA HEALTH CENTER","registration_area_id":"2138","precise_location":null,"abbreviation":"020","state":"09","lga":"16","ward":"09","units":"020","delimitation":"09/16/09/020","remark":"NEW PU"},{"id":"38802","name":"AGIGA P/G NEW LAYOUT","registration_area_id":"2138","precise_location":null,"abbreviation":"021","state":"09","lga":"16","ward":"09","units":"021","delimitation":"09/16/09/021","remark":"NEW PU"},{"id":"38803","name":"CENTRAL MOTOR PARK IGOLI","registration_area_id":"2138","precise_location":null,"abbreviation":"022","state":"09","lga":"16","ward":"09","units":"022","delimitation":"09/16/09/022","remark":"NEW PU"},{"id":"38804","name":"P/G AGIGA OPPOSITE MTN MAST","registration_area_id":"2138","precise_location":null,"abbreviation":"023","state":"09","lga":"16","ward":"09","units":"023","delimitation":"09/16/09/023","remark":"NEW PU"},{"id":"38805","name":"MECHANIC VILLAGE OKUKU ROAD","registration_area_id":"2138","precise_location":null,"abbreviation":"024","state":"09","lga":"16","ward":"09","units":"024","delimitation":"09/16/09/024","remark":"NEW PU"},{"id":"38806","name":"MAMI BY ARMY BARRACK OKUKU RD.","registration_area_id":"2138","precise_location":null,"abbreviation":"025","state":"09","lga":"16","ward":"09","units":"025","delimitation":"09/16/09/025","remark":"NEW PU"},{"id":"38807","name":"GOVT. SECONDARY SCHOOL, IGOLI","registration_area_id":"2138","precise_location":null,"abbreviation":"026","state":"09","lga":"16","ward":"09","units":"026","delimitation":"09/16/09/026","remark":"NEW PU"},{"id":"38808","name":"THOMAS MCGETRICK INSTITUTE OF TECH. IGOLI","registration_area_id":"2138","precise_location":null,"abbreviation":"027","state":"09","lga":"16","ward":"09","units":"027","delimitation":"09/16/09/027","remark":"NEW PU"},{"id":"38809","name":"MOUNT CARMEL SEC. SCH. IGOLI","registration_area_id":"2138","precise_location":null,"abbreviation":"028","state":"09","lga":"16","ward":"09","units":"028","delimitation":"09/16/09/028","remark":"NEW PU"},{"id":"38810","name":"ST. BENS DEM P/S IGOLI III","registration_area_id":"2138","precise_location":null,"abbreviation":"029","state":"09","lga":"16","ward":"09","units":"029","delimitation":"09/16/09/029","remark":"NEW PU"},{"id":"38811","name":"MONIAYA OPPOSIT CHIEF CHARLES ADOGA RD.","registration_area_id":"2138","precise_location":null,"abbreviation":"030","state":"09","lga":"16","ward":"09","units":"030","delimitation":"09/16/09/030","remark":"NEW PU"},{"id":"38812","name":"HIGH COURT IGOLI","registration_area_id":"2138","precise_location":null,"abbreviation":"031","state":"09","lga":"16","ward":"09","units":"031","delimitation":"09/16/09/031","remark":"NEW PU"},{"id":"38813","name":"UKAMUSHA TOWN/ HALL","registration_area_id":"2138","precise_location":null,"abbreviation":"032","state":"09","lga":"16","ward":"09","units":"032","delimitation":"09/16/09/032","remark":"NEW PU"},{"id":"38814","name":"P/G NKIMKOL","registration_area_id":"2138","precise_location":null,"abbreviation":"033","state":"09","lga":"16","ward":"09","units":"033","delimitation":"09/16/09/033","remark":"NEW PU"},{"id":"38815","name":"IKAJOR P/G","registration_area_id":"2138","precise_location":null,"abbreviation":"034","state":"09","lga":"16","ward":"09","units":"034","delimitation":"09/16/09/034","remark":"NEW PU"},{"id":"38816","name":"IKAPTANG TOWN/ HALL","registration_area_id":"2138","precise_location":null,"abbreviation":"035","state":"09","lga":"16","ward":"09","units":"035","delimitation":"09/16/09/035","remark":"NEW PU"},{"id":"38817","name":"OPPOSIT FRSC OFFICE STADIUM","registration_area_id":"2138","precise_location":null,"abbreviation":"036","state":"09","lga":"16","ward":"09","units":"036","delimitation":"09/16/09/036","remark":"NEW PU"},{"id":"38818","name":"SCHOOL OF NURSING IGOLI","registration_area_id":"2138","precise_location":null,"abbreviation":"037","state":"09","lga":"16","ward":"09","units":"037","delimitation":"09/16/09/037","remark":"NEW PU"},{"id":"38819","name":"ISHBORRI MARKET","registration_area_id":"2138","precise_location":null,"abbreviation":"038","state":"09","lga":"16","ward":"09","units":"038","delimitation":"09/16/09/038","remark":"NEW PU"},{"id":"38820","name":"ISHIBORRI MOTOR PARK","registration_area_id":"2138","precise_location":null,"abbreviation":"039","state":"09","lga":"16","ward":"09","units":"039","delimitation":"09/16/09/039","remark":"NEW PU"}]}}