{"2831":{"id":"2831","name":"ILASA II / IKUN / ARAROMI","abbreviation":"11","local_government_id":"245","stateId":13,"lgaId":"03","pollingUnits":[{"id":"53135","name":"ILADO ST. / ILADO / OGBO OWA","registration_area_id":"2831","precise_location":null,"abbreviation":"001","state":"13","lga":"03","ward":"11","units":"001","delimitation":"13/03/11/001","remark":"EXISTING PU"},{"id":"53136","name":"IREGUN ST./ IREGUN","registration_area_id":"2831","precise_location":null,"abbreviation":"002","state":"13","lga":"03","ward":"11","units":"002","delimitation":"13/03/11/002","remark":"EXISTING PU"},{"id":"53137","name":"ISOLO ST. / OKE ODO - ISOLO","registration_area_id":"2831","precise_location":null,"abbreviation":"003","state":"13","lga":"03","ward":"11","units":"003","delimitation":"13/03/11/003","remark":"EXISTING PU"},{"id":"53138","name":"IRO ST. / IRO  I","registration_area_id":"2831","precise_location":null,"abbreviation":"004","state":"13","lga":"03","ward":"11","units":"004","delimitation":"13/03/11/004","remark":"EXISTING PU"},{"id":"53139","name":"IRO ST. / IRO   II","registration_area_id":"2831","precise_location":null,"abbreviation":"005","state":"13","lga":"03","ward":"11","units":"005","delimitation":"13/03/11/005","remark":"EXISTING PU"},{"id":"53140","name":"FIDITI ST. / FIDITI","registration_area_id":"2831","precise_location":null,"abbreviation":"006","state":"13","lga":"03","ward":"11","units":"006","delimitation":"13/03/11/006","remark":"EXISTING PU"},{"id":"53141","name":"OKOROKORO / OKOROKORO","registration_area_id":"2831","precise_location":null,"abbreviation":"007","state":"13","lga":"03","ward":"11","units":"007","delimitation":"13/03/11/007","remark":"EXISTING PU"},{"id":"53142","name":"FRONTAGE OF OLADIPO'S HOUSE / IKUN","registration_area_id":"2831","precise_location":null,"abbreviation":"008","state":"13","lga":"03","ward":"11","units":"008","delimitation":"13/03/11/008","remark":"EXISTING PU"},{"id":"53143","name":"OBA' S PALACE / ARAROMI","registration_area_id":"2831","precise_location":null,"abbreviation":"009","state":"13","lga":"03","ward":"11","units":"009","delimitation":"13/03/11/009","remark":"EXISTING PU"},{"id":"53144","name":"MODEL HEALTH CENTRE IGBOOWA","registration_area_id":"2831","precise_location":null,"abbreviation":"010","state":"13","lga":"03","ward":"11","units":"010","delimitation":"13/03/11/010","remark":"NEW PU"},{"id":"53145","name":"MARKET PLACE IJEU","registration_area_id":"2831","precise_location":null,"abbreviation":"011","state":"13","lga":"03","ward":"11","units":"011","delimitation":"13/03/11/011","remark":"NEW PU"},{"id":"53146","name":"OPEN SPACE AT ISOLO , OPPOSITE THE APOSTOLIC CHURCH, ARAROMI","registration_area_id":"2831","precise_location":null,"abbreviation":"012","state":"13","lga":"03","ward":"11","units":"012","delimitation":"13/03/11/012","remark":"NEW PU"}]}}