{"3356":{"id":"3356","name":"LORJI","abbreviation":"08","local_government_id":"293","stateId":16,"lgaId":"01","pollingUnits":[{"id":"62298","name":"COMMUNITY SCHOOL LORJI I","registration_area_id":"3356","precise_location":null,"abbreviation":"001","state":"16","lga":"01","ward":"08","units":"001","delimitation":"16/01/08/001","remark":"EXISTING PU"},{"id":"62299","name":"COMMUNITY SCHOOL LORJI II","registration_area_id":"3356","precise_location":null,"abbreviation":"002","state":"16","lga":"01","ward":"08","units":"002","delimitation":"16/01/08/002","remark":"EXISTING PU"},{"id":"62300","name":"COMMUNITY SCHOOL LORJI III","registration_area_id":"3356","precise_location":null,"abbreviation":"003","state":"16","lga":"01","ward":"08","units":"003","delimitation":"16/01/08/003","remark":"EXISTING PU"},{"id":"62301","name":"CENTRAL SCHOOL LORJI I","registration_area_id":"3356","precise_location":null,"abbreviation":"004","state":"16","lga":"01","ward":"08","units":"004","delimitation":"16/01/08/004","remark":"EXISTING PU"},{"id":"62302","name":"CENTRAL SCHOOL LORJI II","registration_area_id":"3356","precise_location":null,"abbreviation":"005","state":"16","lga":"01","ward":"08","units":"005","delimitation":"16/01/08/005","remark":"EXISTING PU"},{"id":"62303","name":"CENTRAL SCHOOL LORJI III","registration_area_id":"3356","precise_location":null,"abbreviation":"006","state":"16","lga":"01","ward":"08","units":"006","delimitation":"16/01/08/006","remark":"EXISTING PU"},{"id":"62304","name":"NDIOKWU HALL-EKEOKWU LODGE","registration_area_id":"3356","precise_location":null,"abbreviation":"007","state":"16","lga":"01","ward":"08","units":"007","delimitation":"16/01/08/007","remark":"NEW PU"},{"id":"62305","name":"UMUAGBEDE HALL-NDIOKWU","registration_area_id":"3356","precise_location":null,"abbreviation":"008","state":"16","lga":"01","ward":"08","units":"008","delimitation":"16/01/08/008","remark":"NEW PU"}]}}