{"5844":{"id":"5844","name":"LADE 1","abbreviation":"08","local_government_id":"505","stateId":23,"lgaId":"16","pollingUnits":[{"id":"111824","name":"BONGI LGEA SCH","registration_area_id":"5844","precise_location":null,"abbreviation":"001","state":"23","lga":"16","ward":"08","units":"001","delimitation":"23/16/08/001","remark":"EXISTING PU"},{"id":"111825","name":"CHITTA LGEA SCH","registration_area_id":"5844","precise_location":null,"abbreviation":"002","state":"23","lga":"16","ward":"08","units":"002","delimitation":"23/16/08/002","remark":"EXISTING PU"},{"id":"111826","name":"GBADASHABA LGEA SCH","registration_area_id":"5844","precise_location":null,"abbreviation":"003","state":"23","lga":"16","ward":"08","units":"003","delimitation":"23/16/08/003","remark":"EXISTING PU"},{"id":"111827","name":"MAGYA LGEA SCH","registration_area_id":"5844","precise_location":null,"abbreviation":"004","state":"23","lga":"16","ward":"08","units":"004","delimitation":"23/16/08/004","remark":"EXISTING PU"},{"id":"111828","name":"SUNKUSO LGEA SCH","registration_area_id":"5844","precise_location":null,"abbreviation":"005","state":"23","lga":"16","ward":"08","units":"005","delimitation":"23/16/08/005","remark":"EXISTING PU"},{"id":"111829","name":"SANCHITA OPEN SPACE","registration_area_id":"5844","precise_location":null,"abbreviation":"006","state":"23","lga":"16","ward":"08","units":"006","delimitation":"23/16/08/006","remark":"EXISTING PU"},{"id":"111830","name":"LILE L.G.E.A. SCHOOL","registration_area_id":"5844","precise_location":null,"abbreviation":"007","state":"23","lga":"16","ward":"08","units":"007","delimitation":"23/16/08/007","remark":"NEW PU"},{"id":"111831","name":"GADAWORO L.G.E.A PRY SCHOOL","registration_area_id":"5844","precise_location":null,"abbreviation":"008","state":"23","lga":"16","ward":"08","units":"008","delimitation":"23/16/08/008","remark":"NEW PU"},{"id":"111832","name":"EKATI L.G.E.A. SCHOOL","registration_area_id":"5844","precise_location":null,"abbreviation":"009","state":"23","lga":"16","ward":"08","units":"009","delimitation":"23/16/08/009","remark":"NEW PU"},{"id":"111833","name":"DAKANI L.G.E.A PRY SCHOOL","registration_area_id":"5844","precise_location":null,"abbreviation":"010","state":"23","lga":"16","ward":"08","units":"010","delimitation":"23/16/08/010","remark":"NEW PU"}]}}