{"611":{"id":"611","name":"EASTERN NSIT X","abbreviation":"10","local_government_id":"57","stateId":3,"lgaId":"19","pollingUnits":[{"id":"10698","name":"TOWN HALL, IKOT ESSIEN I","registration_area_id":"611","precise_location":null,"abbreviation":"001","state":"03","lga":"19","ward":"10","units":"001","delimitation":"03/19/10/001","remark":"EXISTING PU"},{"id":"10699","name":"TOWN HALL, IKOT ESSIEN II","registration_area_id":"611","precise_location":null,"abbreviation":"002","state":"03","lga":"19","ward":"10","units":"002","delimitation":"03/19/10/002","remark":"EXISTING PU"},{"id":"10700","name":"PRY SCH, IKOT UYO","registration_area_id":"611","precise_location":null,"abbreviation":"003","state":"03","lga":"19","ward":"10","units":"003","delimitation":"03/19/10/003","remark":"EXISTING PU"},{"id":"10701","name":"VILLAGE SQUARE, AFIA","registration_area_id":"611","precise_location":null,"abbreviation":"004","state":"03","lga":"19","ward":"10","units":"004","delimitation":"03/19/10/004","remark":"EXISTING PU"},{"id":"10702","name":"VILLAGE SQUARE, NDA NSIT","registration_area_id":"611","precise_location":null,"abbreviation":"005","state":"03","lga":"19","ward":"10","units":"005","delimitation":"03/19/10/005","remark":"EXISTING PU"},{"id":"10703","name":"PRY SCH,  NDA NSIT","registration_area_id":"611","precise_location":null,"abbreviation":"006","state":"03","lga":"19","ward":"10","units":"006","delimitation":"03/19/10/006","remark":"EXISTING PU"},{"id":"10704","name":"VILLAGE SQUARE, IKOT ESOP","registration_area_id":"611","precise_location":null,"abbreviation":"007","state":"03","lga":"19","ward":"10","units":"007","delimitation":"03/19/10/007","remark":"EXISTING PU"},{"id":"10705","name":"VILLAGE SQUARE, IKOT UDOFIA","registration_area_id":"611","precise_location":null,"abbreviation":"008","state":"03","lga":"19","ward":"10","units":"008","delimitation":"03/19/10/008","remark":"EXISTING PU"}]}}