{"826":{"id":"826","name":"UGBENE","abbreviation":"12","local_government_id":"75","stateId":4,"lgaId":"06","pollingUnits":[{"id":"13859","name":"CENTRAL SCHOOL, UGBENE","registration_area_id":"826","precise_location":null,"abbreviation":"001","state":"04","lga":"06","ward":"12","units":"001","delimitation":"04/06/12/001","remark":"EXISTING PU"},{"id":"13860","name":"COMM. PRY. SCHOOL","registration_area_id":"826","precise_location":null,"abbreviation":"002","state":"04","lga":"06","ward":"12","units":"002","delimitation":"04/06/12/002","remark":"EXISTING PU"},{"id":"13861","name":"OKPUOBA VILLAGE SQUARE","registration_area_id":"826","precise_location":null,"abbreviation":"003","state":"04","lga":"06","ward":"12","units":"003","delimitation":"04/06/12/003","remark":"EXISTING PU"},{"id":"13862","name":"UMUALOR SQUARE","registration_area_id":"826","precise_location":null,"abbreviation":"004","state":"04","lga":"06","ward":"12","units":"004","delimitation":"04/06/12/004","remark":"EXISTING PU"},{"id":"13863","name":"AFOR UGBENE SQUARE","registration_area_id":"826","precise_location":null,"abbreviation":"005","state":"04","lga":"06","ward":"12","units":"005","delimitation":"04/06/12/005","remark":"EXISTING PU"},{"id":"13864","name":"IFITEORA SQUARE","registration_area_id":"826","precise_location":null,"abbreviation":"006","state":"04","lga":"06","ward":"12","units":"006","delimitation":"04/06/12/006","remark":"EXISTING PU"},{"id":"13865","name":"UMUNOKWAM SQUARE","registration_area_id":"826","precise_location":null,"abbreviation":"007","state":"04","lga":"06","ward":"12","units":"007","delimitation":"04/06/12/007","remark":"EXISTING PU"},{"id":"13866","name":"UMUEMEMU SQUARE","registration_area_id":"826","precise_location":null,"abbreviation":"008","state":"04","lga":"06","ward":"12","units":"008","delimitation":"04/06/12/008","remark":"EXISTING PU"}]}}